LICENSE
README.md
setup.py
charLM.egg-info/PKG-INFO
charLM.egg-info/SOURCES.txt
charLM.egg-info/dependency_links.txt
charLM.egg-info/requires.txt
charLM.egg-info/top_level.txt
charlm/__init__.py
charlm/charlm.py
charlm/ngram.py